blkinfo/__init__.py
blkinfo/diskstats.py
blkinfo/errors.py
blkinfo/filters.py
blkinfo/wrappers.py
blkinfo-0.1.2.dist-info/LICENSE
blkinfo-0.1.2.dist-info/METADATA
blkinfo-0.1.2.dist-info/WHEEL
blkinfo-0.1.2.dist-info/top_level.txt
blkinfo-0.1.2.dist-info/RECORD
