Metadata-Version: 2.1
Name: blkinfo
Version: 0.1.2
Summary: blkinfo is a python package to list information about all available or the specified block devices.
Home-page: https://github.com/grinrag/blkinfo
Author: Gennadii Altukhov
Author-email: galt@redhat.com
License: GPLv3
Keywords: lsblk disk blockdevice blockinfo blkinfo iscsi
Platform: UNKNOWN
Classifier: Development Status :: 4 - Beta
Classifier: Programming Language :: Python
Classifier: Programming Language :: Python :: 3
Classifier: Topic :: Software Development :: Libraries :: Python Modules
